protorepo/__init__.py
protorepo/messages_pb2.py
protorepo/messages_pb2.pyi
protorepo-0.4.0.dist-info/METADATA
protorepo-0.4.0.dist-info/WHEEL
protorepo-0.4.0.dist-info/top_level.txt
protorepo-0.4.0.dist-info/RECORD
