Metadata-Version: 2.1
Name: protorepo
Version: 0.4.0
Summary: Antiplagiarism protorepo
Home-page: https://github.com/no-plagiarism/protorepo
Author: Danylo Halaiko
Author-email: d9nich@pm.me
Project-URL: Bug Tracker, https://github.com/no-plagiarism/protorepo/issues
Classifier: Programming Language :: Python :: 3
Requires-Python: >=3.8
Requires-Dist: protobuf
